<annotation>
  <folder></folder>
  <filename>204.onion-759.jpg</filename>
  <source>
    <database>Unknown</database>
    <annotation>Unknown</annotation>
    <image>Unknown</image>
  </source>
  <size>
    <width>759</width>
    <height>422</height>
    <depth></depth>
  </size>
  <segmented>0</segmented>
  <object>
    <name>onions</name>
    <truncated>0</truncated>
    <occluded>0</occluded>
    <difficult>0</difficult>
    <bndbox>
      <xmin>86.78</xmin>
      <ymin>270.96</ymin>
      <xmax>306.38</xmax>
      <ymax>394.42</ymax>
    </bndbox>
    <attributes>
      <attribute>
        <name>states</name>
        <value>whole</value>
      </attribute>
      <attribute>
        <name>rotation</name>
        <value>0.0</value>
      </attribute>
    </attributes>
  </object>
  <object>
    <name>onions</name>
    <truncated>0</truncated>
    <occluded>0</occluded>
    <difficult>0</difficult>
    <bndbox>
      <xmin>323.58</xmin>
      <ymin>87.79</ymin>
      <xmax>464.75</xmax>
      <ymax>185.44</ymax>
    </bndbox>
    <attributes>
      <attribute>
        <name>states</name>
        <value>peeled</value>
      </attribute>
      <attribute>
        <name>rotation</name>
        <value>0.0</value>
      </attribute>
    </attributes>
  </object>
</annotation>
